<?xml version='1.0' encoding='UTF-8'?>
<DEFECTS><DEFECT><SFA><FILEPATH>c:\users\dell\desktop\toothseg\trimesh_framework\trimesh_framework\src\</FILEPATH><FILENAME>filter.cc</FILENAME><LINE>0</LINE><COLUMN>0</COLUMN></SFA><DEFECTCODE>6993</DEFECTCODE><DESCRIPTION>Code analysis ignores OpenMP constructs; analyzing single-threaded code.</DESCRIPTION><FUNCTION></FUNCTION><DECORATED></DECORATED><FUNCLINE>0</FUNCLINE><PATH/></DEFECT><DEFECT><SFA><FILEPATH>c:\users\dell\desktop\toothseg\trimesh_framework\trimesh_framework\src\</FILEPATH><FILENAME>filter.cc</FILENAME><LINE>454</LINE><COLUMN>16</COLUMN></SFA><DEFECTCODE>6246</DEFECTCODE><DESCRIPTION>Local declaration of 'v0' hides declaration of the same name in outer scope. For additional information, see previous declaration at line '441' of 'c:\users\dell\desktop\toothseg\trimesh_framework\trimesh_framework\src\filter.cc'.</DESCRIPTION><FUNCTION>trimesh::orient</FUNCTION><DECORATED>?orient@trimesh@@YAXPAVTriMesh@1@@Z</DECORATED><FUNCLINE>385</FUNCLINE><PATH><SFA><FILEPATH>c:\users\dell\desktop\toothseg\trimesh_framework\trimesh_framework\src\</FILEPATH><FILENAME>filter.cc</FILENAME><LINE>441</LINE><COLUMN>15</COLUMN></SFA></PATH></DEFECT><DEFECT><SFA><FILEPATH>c:\users\dell\desktop\toothseg\trimesh_framework\trimesh_framework\src\</FILEPATH><FILENAME>filter.cc</FILENAME><LINE>455</LINE><COLUMN>16</COLUMN></SFA><DEFECTCODE>6246</DEFECTCODE><DESCRIPTION>Local declaration of 'v1' hides declaration of the same name in outer scope. For additional information, see previous declaration at line '442' of 'c:\users\dell\desktop\toothseg\trimesh_framework\trimesh_framework\src\filter.cc'.</DESCRIPTION><FUNCTION>trimesh::orient</FUNCTION><DECORATED>?orient@trimesh@@YAXPAVTriMesh@1@@Z</DECORATED><FUNCLINE>385</FUNCLINE><PATH><SFA><FILEPATH>c:\users\dell\desktop\toothseg\trimesh_framework\trimesh_framework\src\</FILEPATH><FILENAME>filter.cc</FILENAME><LINE>442</LINE><COLUMN>15</COLUMN></SFA></PATH></DEFECT><DEFECT><SFA><FILEPATH>c:\users\dell\desktop\toothseg\trimesh_framework\trimesh_framework\src\</FILEPATH><FILENAME>filter.cc</FILENAME><LINE>456</LINE><COLUMN>16</COLUMN></SFA><DEFECTCODE>6246</DEFECTCODE><DESCRIPTION>Local declaration of 'v2' hides declaration of the same name in outer scope. For additional information, see previous declaration at line '443' of 'c:\users\dell\desktop\toothseg\trimesh_framework\trimesh_framework\src\filter.cc'.</DESCRIPTION><FUNCTION>trimesh::orient</FUNCTION><DECORATED>?orient@trimesh@@YAXPAVTriMesh@1@@Z</DECORATED><FUNCLINE>385</FUNCLINE><PATH><SFA><FILEPATH>c:\users\dell\desktop\toothseg\trimesh_framework\trimesh_framework\src\</FILEPATH><FILENAME>filter.cc</FILENAME><LINE>443</LINE><COLUMN>15</COLUMN></SFA></PATH></DEFECT></DEFECTS>